Workbook

Sheet INVENTORY MANAGEMENT
A2: SL. No. | B2: PRODUCT | C2: OPENING STOCK | E2: Opening STOCK VALUE | G2: NEW STOCK | H2: CLOSING STOCK | J2: SALE | K2: Closing STOCK VALUE | M2: EMPTY BOTTLE
A3: 1 | B3: CEASAR BRANDY | C3: 1000 ml | E3: =(('[1]PURCHASE COST'!D2/12)+(('[1]PURCHASE COST'!D2/12)*3.87%))*D3 -> 0 | F3: =SUM(E3:E7) -> 3531.303 | H3: 1000 ml | L3: =K3+K4+K5+K6+K7 -> 3391.9095 | M3: =D3-I3 -> 0
C4: 750 ml | D4: 3 | E4: =(('[1]PURCHASE COST'!D3/12)+(('[1]PURCHASE COST'!D3/12)*3.87%))*D4 -> 3484.8385 | H4: 750 ml | I4: 2 | J4: =(D4+G4)-I4 -> 1 | K4: =(('[1]PURCHASE COST'!D3/12)+(('[1]PURCHASE COST'!D3/12)*3.87%))*I4 -> 2323.2257 | M4: =D4-I4 -> 1
C5: 500 ml | E5: =(('[1]PURCHASE COST'!D4/18)+(('[1]PURCHASE COST'!D4/18)*3.87%))*D5 -> 0 | H5: 500 ml | J5: =(D5+G5)-I5 -> 0 | K5: =(('[1]PURCHASE COST'!D4/18)+(('[1]PURCHASE COST'!D4/18)*3.87%))*I5 -> 0 | M5: =D5-I5 -> 0
C6: 375 ml | E6: =(('[1]PURCHASE COST'!D5/24)+(('[1]PURCHASE COST'!D5/24)*3.87%))*D6 -> 0 | H6: 375 ml | J6: =(D6+G6)-I6 -> 0 | K6: =(('[1]PURCHASE COST'!D5/24)+(('[1]PURCHASE COST'!D5/24)*3.87%))*I6 -> 0 | M6: =D6-I6 -> 0
C7: 60 ml | D7: 0.5 | E7: =((('[1]PURCHASE COST'!D3/12)+(('[1]PURCHASE COST'!D3/12)*3.87%))/12.5)*D7 -> 46.464513 | H7: 60 ml | I7: 11.5 | J7: =((((D4+G4)-I4)*12.5)+D7)-I7 -> 1.5 | K7: =((('[1]PURCHASE COST'!D3/12)+(('[1]PURCHASE COST'!D3/12)*3.87%))/12.5)*I7 -> 1068.6838
A8: 2 | B8: M.C BRANDY | C8: 1000 ml | D8: 115 | E8: =(('[1]PURCHASE COST'!D7/9)+(('[1]PURCHASE COST'!D7/9)*3.87%))*D8 -> 89189.707 | F8: =SUM(E8:E12) -> 103036.73 | H8: 1000 ml | I8: 110 | K8: =(('[1]PURCHASE COST'!D7/9)+(('[1]PURCHASE COST'!D7/9)*3.87%))*I8 -> 85311.893 | L8: =K8+K9+K10+K11+K12 -> 99252.926 | M8: =D8-I8 -> 5
C9: 750 ml | E9: =(('[1]PURCHASE COST'!D8/12)+(('[1]PURCHASE COST'!D8/12)*3.87%))*D9 -> 0 | H9: 750 ml | J9: =(D9+G9)-I9 -> 0 | K9: =(('[1]PURCHASE COST'!D8/12)+(('[1]PURCHASE COST'!D8/12)*3.87%))*I9 -> 0 | M9: =D9-I9 -> 0
C10: 500 ml | D10: 35 | E10: =(('[1]PURCHASE COST'!D9/18)+(('[1]PURCHASE COST'!D9/18)*3.87%))*D10 -> 13329.983 | H10: 500 ml | I10: 35 | J10: =(D10+G10)-I10 -> 0 | K10: =(('[1]PURCHASE COST'!D9/18)+(('[1]PURCHASE COST'!D9/18)*3.87%))*I10 -> 13329.983 | M10: =D10-I10 -> 0
C11: 375 ml | D11: 40 | E11: =(('[1]PURCHASE COST'!D10/24)+(('[1]PURCHASE COST'!D10/24)*3.87%))*D11 -> 0 | H11: 375 ml | I11: 39 | J11: =(D11+G11)-I11 -> 1 | K11: =(('[1]PURCHASE COST'!D10/24)+(('[1]PURCHASE COST'!D10/24)*3.87%))*I11 -> 0 | M11: =D11-I11 -> 1
C12: 60 ml | D12: 11 | E12: =((('[1]PURCHASE COST'!D7/9)+(('[1]PURCHASE COST'!D7/9)*3.87%))/16.5)*D12 -> 517.04178 | H12: 60 ml | I12: 13 | J12: =((((D8+G8)-I8)*16.5)+D12)-I12 -> 80.5 | K12: =((('[1]PURCHASE COST'!D7/9)+(('[1]PURCHASE COST'!D7/9)*3.87%))/16.5)*I12 -> 611.04937 | M12: =D12-I12 -> -2
A13: 3 | B13: MGM ORANGE VODKA | C13: 1000 ml | D13: 118 | E13: =(('[1]PURCHASE COST'!D12/9)+(('[1]PURCHASE COST'!D12/9)*3.87%))*D13 -> 87430.841 | F13: =SUM(E13:E17) -> 89899.38 | H13: 1000 ml | I13: 113 | K13: =(('[1]PURCHASE COST'!D12/9)+(('[1]PURCHASE COST'!D12/9)*3.87%))*I13 -> 83726.145 | L13: =K13+K14+K15+K16+K17 -> 86688.643 | M13: =D13-I13 -> 5
C14: 750 ml | E14: =(('[1]PURCHASE COST'!D13/12)+(('[1]PURCHASE COST'!D13/12)*3.87%))*D14 -> 0 | H14: 750 ml | J14: =(D14+G14)-I14 -> 0 | K14: =(('[1]PURCHASE COST'!D13/12)+(('[1]PURCHASE COST'!D13/12)*3.87%))*I14 -> 0 | M14: =D14-I14 -> 0
C15: 500 ml | E15: =(('[1]PURCHASE COST'!D14/18)+(('[1]PURCHASE COST'!D14/18)*3.87%))*D15 -> 0 | H15: 500 ml | J15: =(D15+G15)-I15 -> 0 | K15: =(('[1]PURCHASE COST'!D14/18)+(('[1]PURCHASE COST'!D14/18)*3.87%))*I15 -> 0 | M15: =D15-I15 -> 0
C16: 375 ml | D16: 8 | E16: =(('[1]PURCHASE COST'!D15/24)+(('[1]PURCHASE COST'!D15/24)*3.87%))*D16 -> 2423.6333 | H16: 375 ml | I16: 8 | J16: =(D16+G16)-I16 -> 0 | K16: =(('[1]PURCHASE COST'!D15/24)+(('[1]PURCHASE COST'!D15/24)*3.87%))*I16 -> 2423.6333 | M16: =D16-I16 -> 0
C17: 60 ml | D17: 1 | E17: =((('[1]PURCHASE COST'!D12/9)+(('[1]PURCHASE COST'!D12/9)*3.87%))/16.5)*D17 -> 44.905414 | H17: 60 ml | I17: 12 | J17: =((((D13+G13)-I13)*16.5)+D17)-I17 -> 71.5 | K17: =((('[1]PURCHASE COST'!D12/9)+(('[1]PURCHASE COST'!D12/9)*3.87%))/16.5)*I17 -> 538.86497
A18: 4 | B18: MANSION HOUSE BRANDY | C18: 1000 ml | D18: 18 | E18: =(('[1]PURCHASE COST'!D17/9)+(('[1]PURCHASE COST'!D17/9)*3.87%))*D18 -> 17117.776 | F18: =SUM(E18:E22) -> 33637.609 | H18: 1000 ml | I18: 18 | K18: =(('[1]PURCHASE COST'!D17/9)+(('[1]PURCHASE COST'!D17/9)*3.87%))*I18 -> 17117.776 | L18: =K18+K19+K20+K21+K22 -> 33090.07 | M18: =D18-I18 -> 0
C19: 750 ml | E19: =(('[1]PURCHASE COST'!D18/12)+(('[1]PURCHASE COST'!D18/12)*3.87%))*D19 -> 0 | H19: 750 ml | J19: =(D19+G19)-I19 -> 0 | K19: =(('[1]PURCHASE COST'!D18/12)+(('[1]PURCHASE COST'!D18/12)*3.87%))*I19 -> 0 | M19: =D19-I19 -> 0
C20: 500 ml | D20: 14 | E20: =(('[1]PURCHASE COST'!D19/18)+(('[1]PURCHASE COST'!D19/18)*3.87%))*D20 -> 6980.064 | H20: 500 ml | I20: 14 | J20: =(D20+G20)-I20 -> 0 | K20: =(('[1]PURCHASE COST'!D19/18)+(('[1]PURCHASE COST'!D19/18)*3.87%))*I20 -> 6980.064 | M20: =D20-I20 -> 0
C21: 375 ml | D21: 19 | E21: =(('[1]PURCHASE COST'!D20/24)+(('[1]PURCHASE COST'!D20/24)*3.87%))*D21 -> 8732.8702 | H21: 375 ml | I21: 19 | J21: =(D21+G21)-I21 -> 0 | K21: =(('[1]PURCHASE COST'!D20/24)+(('[1]PURCHASE COST'!D20/24)*3.87%))*I21 -> 8732.8702 | M21: =D21-I21 -> 0
C22: 60 ml | D22: 14 | E22: =((('[1]PURCHASE COST'!D17/9)+(('[1]PURCHASE COST'!D17/9)*3.87%))/16.5)*D22 -> 806.89853 | H22: 60 ml | I22: 4.5 | J22: =((((D18+G18)-I18)*16.5)+D22)-I22 -> 9.5 | K22: =((('[1]PURCHASE COST'!D17/9)+(('[1]PURCHASE COST'!D17/9)*3.87%))/16.5)*I22 -> 259.36024
A23: 5 | B23: OLD CASK RUM | C23: 1000 ml | E23: =(('[1]PURCHASE COST'!D22/9)+(('[1]PURCHASE COST'!D22/9)*3.87%))*D23 -> 0 | F23: =SUM(E23:E27) -> 1217.867 | H23: 1000 ml | J23: =(D23+G23)-I23 -> 0 | K23: =(('[1]PURCHASE COST'!D22/9)+(('[1]PURCHASE COST'!D22/9)*3.87%))*I23 -> 0 | L23: =K23+K24+K25+K26+K27 -> 1217.867 | M23: =D23-I23 -> 0
C24: 750 ml | E24: =(('[1]PURCHASE COST'!D23/12)+(('[1]PURCHASE COST'!D23/12)*3.87%))*D24 -> 0 | H24: 750 ml | J24: =(D24+G24)-I24 -> 0 | K24: =(('[1]PURCHASE COST'!D23/12)+(('[1]PURCHASE COST'!D23/12)*3.87%))*I24 -> 0 | M24: =D24-I24 -> 0
C25: 500 ml | D25: 3 | E25: =(('[1]PURCHASE COST'!D24/18)+(('[1]PURCHASE COST'!D24/18)*3.87%))*D25 -> 1125.2583 | H25: 500 ml | I25: 3 | J25: =(D25+G25)-I25 -> 0 | K25: =(('[1]PURCHASE COST'!D24/18)+(('[1]PURCHASE COST'!D24/18)*3.87%))*I25 -> 1125.2583 | M25: =D25-I25 -> 0
C26: 375 ml | E26: =(('[1]PURCHASE COST'!D25/24)+(('[1]PURCHASE COST'!D25/24)*3.87%))*D26 -> 0 | H26: 375 ml | J26: =(D26+G26)-I26 -> 0 | K26: =(('[1]PURCHASE COST'!D25/24)+(('[1]PURCHASE COST'!D25/24)*3.87%))*I26 -> 0 | M26: =D26-I26 -> 0
C27: 60 ml | D27: 2 | E27: =((('[1]PURCHASE COST'!D22/9)+(('[1]PURCHASE COST'!D22/9)*3.87%))/16.5)*D27 -> 92.608673 | H27: 60 ml | I27: 2 | J27: =((((D23+G23)-I23)*16.5)+D27)-I27 -> 0 | K27: =((('[1]PURCHASE COST'!D22/9)+(('[1]PURCHASE COST'!D22/9)*3.87%))/16.5)*I27 -> 92.608673
A28: 6 | B28: CR. NEPOLEAN BRANDY | C28: 1000 ml | D28: 33 | E28: =(('[1]PURCHASE COST'!D27/9)+(('[1]PURCHASE COST'!D27/9)*3.87%))*D28 -> 28259.565 | F28: =SUM(E28:E32) -> 28337.415 | H28: 1000 ml | I28: 32 | J28: =(D28+G28)-I28 -> 1 | K28: =(('[1]PURCHASE COST'!D27/9)+(('[1]PURCHASE COST'!D27/9)*3.87%))*I28 -> 27403.214 | L28: =K28+K29+K30+K31+K32 -> 27922.214 | M28: =D28-I28 -> 1
C29: 750 ml | E29: =(('[1]PURCHASE COST'!D28/12)+(('[1]PURCHASE COST'!D28/12)*3.87%))*D29 -> 0 | H29: 750 ml | J29: =(D29+G29)-I29 -> 0 | K29: =(('[1]PURCHASE COST'!D28/12)+(('[1]PURCHASE COST'!D28/12)*3.87%))*I29 -> 0 | M29: =D29-I29 -> 0
C30: 500 ml | E30: =(('[1]PURCHASE COST'!D29/18)+(('[1]PURCHASE COST'!D29/18)*3.87%))*D30 -> 0 | H30: 500 ml | J30: =(D30+G30)-I30 -> 0 | K30: =(('[1]PURCHASE COST'!D29/18)+(('[1]PURCHASE COST'!D29/18)*3.87%))*I30 -> 0 | M30: =D30-I30 -> 0
C31: 375 ml | E31: =(('[1]PURCHASE COST'!D30/24)+(('[1]PURCHASE COST'!D30/24)*3.87%))*D31 -> 0 | H31: 375 ml | J31: =(D31+G31)-I31 -> 0 | K31: =(('[1]PURCHASE COST'!D30/24)+(('[1]PURCHASE COST'!D30/24)*3.87%))*I31 -> 0 | M31: =D31-I31 -> 0
C32: 60 ml | D32: 1.5 | E32: =((('[1]PURCHASE COST'!D27/9)+(('[1]PURCHASE COST'!D27/9)*3.87%))/16.5)*D32 -> 77.85004 | H32: 60 ml | I32: 10 | J32: =((((D28+G28)-I28)*16.5)+D32)-I32 -> 8 | K32: =((('[1]PURCHASE COST'!D27/9)+(('[1]PURCHASE COST'!D27/9)*3.87%))/16.5)*I32 -> 519.00027
A33: 7 | B33: HONEY BEE BRANDY | C33: 1000 ml | D33: 24 | E33: =(('[1]PURCHASE COST'!D32/9)+(('[1]PURCHASE COST'!D32/9)*3.87%))*D33 -> 18613.504 | F33: =SUM(E33:E37) -> 26742.092 | H33: 1000 ml | I33: 23 | J33: =(D33+G33)-I33 -> 1 | K33: =(('[1]PURCHASE COST'!D32/9)+(('[1]PURCHASE COST'!D32/9)*3.87%))*I33 -> 17837.941 | L33: =K33+K34+K35+K36+K37 -> 26131.043 | M33: =D33-I33 -> 1
C34: 750 ml | E34: =(('[1]PURCHASE COST'!D33/12)+(('[1]PURCHASE COST'!D33/12)*3.87%))*D34 -> 0 | H34: 750 ml | J34: =(D34+G34)-I34 -> 0 | K34: =(('[1]PURCHASE COST'!D33/12)+(('[1]PURCHASE COST'!D33/12)*3.87%))*I34 -> 0 | M34: =D34-I34 -> 0
C35: 500 ml | E35: =(('[1]PURCHASE COST'!D34/18)+(('[1]PURCHASE COST'!D34/18)*3.87%))*D35 -> 0 | H35: 500 ml | J35: =(D35+G35)-I35 -> 0 | K35: =(('[1]PURCHASE COST'!D34/18)+(('[1]PURCHASE COST'!D34/18)*3.87%))*I35 -> 0 | M35: =D35-I35 -> 0
C36: 375 ml | D36: 25 | E36: =(('[1]PURCHASE COST'!D35/24)+(('[1]PURCHASE COST'!D35/24)*3.87%))*D36 -> 7682.0521 | H36: 375 ml | I36: 25 | J36: =(D36+G36)-I36 -> 0 | K36: =(('[1]PURCHASE COST'!D35/24)+(('[1]PURCHASE COST'!D35/24)*3.87%))*I36 -> 7682.0521 | M36: =D36-I36 -> 0
C37: 60 ml | D37: 9.5 | E37: =((('[1]PURCHASE COST'!D32/9)+(('[1]PURCHASE COST'!D32/9)*3.87%))/16.5)*D37 -> 446.53608 | H37: 60 ml | I37: 13 | J37: =((((D33+G33)-I33)*16.5)+D37)-I37 -> 13 | K37: =((('[1]PURCHASE COST'!D32/9)+(('[1]PURCHASE COST'!D32/9)*3.87%))/16.5)*I37 -> 611.04937
A38: 8 | B38: OFFICER CHOICE BRANDY | C38: 1000 ml | D38: 14 | E38: =(('[1]PURCHASE COST'!D37/9)+(('[1]PURCHASE COST'!D37/9)*3.87%))*D38 -> 12150.482 | F38: =SUM(E38:E42) -> 12387.179 | H38: 1000 ml | I38: 13 | K38: =(('[1]PURCHASE COST'!D37/9)+(('[1]PURCHASE COST'!D37/9)*3.87%))*I38 -> 11282.59 | L38: =K38+K39+K40+K41+K42 -> 11650.787 | M38: =D38-I38 -> 1
C39: 750 ml | E39: =(('[1]PURCHASE COST'!D38/12)+(('[1]PURCHASE COST'!D38/12)*3.87%))*D39 -> 0 | H39: 750 ml | J39: =(D39+G39)-I39 -> 0 | K39: =(('[1]PURCHASE COST'!D38/12)+(('[1]PURCHASE COST'!D38/12)*3.87%))*I39 -> 0 | M39: =D39-I39 -> 0
C40: 500 ml | E40: =(('[1]PURCHASE COST'!D39/18)+(('[1]PURCHASE COST'!D39/18)*3.87%))*D40 -> 0 | H40: 500 ml | J40: =(D40+G40)-I40 -> 0 | K40: =(('[1]PURCHASE COST'!D39/18)+(('[1]PURCHASE COST'!D39/18)*3.87%))*I40 -> 0 | M40: =D40-I40 -> 0
C41: 375 ml | E41: =(('[1]PURCHASE COST'!D40/24)+(('[1]PURCHASE COST'!D40/24)*3.87%))*D41 -> 0 | H41: 375 ml | J41: =(D41+G41)-I41 -> 0 | K41: =(('[1]PURCHASE COST'!D40/24)+(('[1]PURCHASE COST'!D40/24)*3.87%))*I41 -> 0 | M41: =D41-I41 -> 0
C42: 60 ml | D42: 4.5 | E42: =((('[1]PURCHASE COST'!D37/9)+(('[1]PURCHASE COST'!D37/9)*3.87%))/16.5)*D42 -> 236.6977 | H42: 60 ml | I42: 7 | J42: =((((D38+G38)-I38)*16.5)+D42)-I42 -> 14 | K42: =((('[1]PURCHASE COST'!D37/9)+(('[1]PURCHASE COST'!D37/9)*3.87%))/16.5)*I42 -> 368.19642
A43: 9 | B43: 8 P.M EXCELLENCY BRANDY | C43: 1000 ml | D43: 349 | E43: =(('[1]PURCHASE COST'!D42/9)+(('[1]PURCHASE COST'!D42/9)*3.87%))*D43 -> 242476.44 | F43: =SUM(E43:E47) -> 254473.42 | H43: 1000 ml | I43: 319 | K43: =(('[1]PURCHASE COST'!D42/9)+(('[1]PURCHASE COST'!D42/9)*3.87%))*I43 -> 221633.19 | L43: =K43+K44+K45+K46+K47 -> 233735.44 | M43: =D43-I43 -> 30
C44: 750 ml | E44: =(('[1]PURCHASE COST'!D43/12)+(('[1]PURCHASE COST'!D43/12)*3.87%))*D44 -> 0 | H44: 750 ml | J44: =(D44+G44)-I44 -> 0 | K44: =(('[1]PURCHASE COST'!D43/12)+(('[1]PURCHASE COST'!D43/12)*3.87%))*I44 -> 0 | M44: =D44-I44 -> 0
C45: 500 ml | D45: 33 | E45: =(('[1]PURCHASE COST'!D44/18)+(('[1]PURCHASE COST'!D44/18)*3.87%))*D45 -> 11996.985 | H45: 500 ml | I45: 33 | J45: =(D45+G45)-I45 -> 0 | K45: =(('[1]PURCHASE COST'!D44/18)+(('[1]PURCHASE COST'!D44/18)*3.87%))*I45 -> 11996.985 | M45: =D45-I45 -> 0
C46: 375 ml | E46: =(('[1]PURCHASE COST'!D45/24)+(('[1]PURCHASE COST'!D45/24)*3.87%))*D46 -> 0 | H46: 375 ml | J46: =(D46+G46)-I46 -> 0 | K46: =(('[1]PURCHASE COST'!D45/24)+(('[1]PURCHASE COST'!D45/24)*3.87%))*I46 -> 0 | M46: =D46-I46 -> 0
C47: 60 ml | D47: 0 | E47: =((('[1]PURCHASE COST'!D42/9)+(('[1]PURCHASE COST'!D42/9)*3.87%))/16.5)*D47 -> 0 | H47: 60 ml | I47: 2.5 | J47: =((((D43+G43)-I43)*16.5)+D47)-I47 -> 492.5 | K47: =((('[1]PURCHASE COST'!D42/9)+(('[1]PURCHASE COST'!D42/9)*3.87%))/16.5)*I47 -> 105.26892
A48: 10 | B48: WHITE MISCHIEF BRANDY | C48: 1000 ml | D48: 23 | E48: =(('[1]PURCHASE COST'!D47/9)+(('[1]PURCHASE COST'!D47/9)*3.87%))*D48 -> 17837.941 | F48: =SUM(E48:E52) -> 17931.949 | H48: 1000 ml | I48: 23 | K48: =(('[1]PURCHASE COST'!D47/9)+(('[1]PURCHASE COST'!D47/9)*3.87%))*I48 -> 17837.941 | L48: =K48+K49+K50+K51+K52 -> 17931.949 | M48: =D48-I48 -> 0
C49: 750 ml | E49: =(('[1]PURCHASE COST'!D48/12)+(('[1]PURCHASE COST'!D48/12)*3.87%))*D49 -> 0 | H49: 750 ml | J49: =(D49+G49)-I49 -> 0 | K49: =(('[1]PURCHASE COST'!D48/12)+(('[1]PURCHASE COST'!D48/12)*3.87%))*I49 -> 0 | M49: =D49-I49 -> 0
C50: 500 ml | E50: =(('[1]PURCHASE COST'!D49/18)+(('[1]PURCHASE COST'!D49/18)*3.87%))*D50 -> 0 | H50: 500 ml | J50: =(D50+G50)-I50 -> 0 | K50: =(('[1]PURCHASE COST'!D49/18)+(('[1]PURCHASE COST'!D49/18)*3.87%))*I50 -> 0 | M50: =D50-I50 -> 0
C51: 375 ml | E51: =(('[1]PURCHASE COST'!D50/24)+(('[1]PURCHASE COST'!D50/24)*3.87%))*D51 -> 0 | H51: 375 ml | J51: =(D51+G51)-I51 -> 0 | K51: =(('[1]PURCHASE COST'!D50/24)+(('[1]PURCHASE COST'!D50/24)*3.87%))*I51 -> 0 | M51: =D51-I51 -> 0
C52: 60 ml | D52: 2 | E52: =((('[1]PURCHASE COST'!D47/9)+(('[1]PURCHASE COST'!D47/9)*3.87%))/16.5)*D52 -> 94.007596 | H52: 60 ml | I52: 2 | J52: =((((D48+G48)-I48)*16.5)+D52)-I52 -> 0 | K52: =((('[1]PURCHASE COST'!D47/9)+(('[1]PURCHASE COST'!D47/9)*3.87%))/16.5)*I52 -> 94.007596
A53: 11 | B53: KEYRON BRANDY | C53: 1000 ml | E53: =(('[1]PURCHASE COST'!D52/9)+(('[1]PURCHASE COST'!D52/9)*3.87%))*D53 -> 0 | F53: =SUM(E53:E57) -> 3772.5584 | H53: 1000 ml | J53: =(D53+G53)-I53 -> 0 | K53: =(('[1]PURCHASE COST'!D52/9)+(('[1]PURCHASE COST'!D52/9)*3.87%))*I53 -> 0 | L53: =K53+K54+K55+K56+K57 -> 3772.5584 | M53: =D53-I53 -> 0
C54: 750 ml | D54: 3 | E54: =(('[1]PURCHASE COST'!D53/12)+(('[1]PURCHASE COST'!D53/12)*3.87%))*D54 -> 3536.7735 | H54: 750 ml | I54: 3 | J54: =(D54+G54)-I54 -> 0 | K54: =(('[1]PURCHASE COST'!D53/12)+(('[1]PURCHASE COST'!D53/12)*3.87%))*I54 -> 3536.7735 | M54: =D54-I54 -> 0
C55: 500 ml | E55: =(('[1]PURCHASE COST'!D54/18)+(('[1]PURCHASE COST'!D54/18)*3.87%))*D55 -> 0 | H55: 500 ml | J55: =(D55+G55)-I55 -> 0 | K55: =(('[1]PURCHASE COST'!D54/18)+(('[1]PURCHASE COST'!D54/18)*3.87%))*I55 -> 0 | M55: =D55-I55 -> 0
C56: 375 ml | E56: =(('[1]PURCHASE COST'!D55/24)+(('[1]PURCHASE COST'!D55/24)*3.87%))*D56 -> 0 | H56: 375 ml | J56: =(D56+G56)-I56 -> 0 | K56: =(('[1]PURCHASE COST'!D55/24)+(('[1]PURCHASE COST'!D55/24)*3.87%))*I56 -> 0 | M56: =D56-I56 -> 0
C57: 60 ml | D57: 2.5 | E57: =((('[1]PURCHASE COST'!D53/12)+(('[1]PURCHASE COST'!D53/12)*3.87%))/12.5)*D57 -> 235.7849 | H57: 60 ml | I57: 2.5 | J57: =((((D53+G53)-I53)*16.5)+D57)-I57 -> 0 | K57: =((('[1]PURCHASE COST'!D53/12)+(('[1]PURCHASE COST'!D53/12)*3.87%))/12.5)*I57 -> 235.7849
A60: 12 | B60: BUDGET RUM | C60: 1000 ml | E60: =(('[1]PURCHASE COST'!D59/9)+(('[1]PURCHASE COST'!D59/9)*3.87%))*D60 -> 0 | F60: =E60+E61+E62+E63+E64 -> 224173.49 | H60: 1000 ml | J60: =(D60+G60)-I60 -> 0 | K60: =(('[1]PURCHASE COST'!D59/9)+(('[1]PURCHASE COST'!D59/9)*3.87%))*I60 -> 0 | L60: =K60+K61+K62+K63+K64 -> 224089.14 | M60: =D60-I60 -> 0
C61: 750 ml | E61: =(('[1]PURCHASE COST'!D60/12)+(('[1]PURCHASE COST'!D60/12)*3.87%))*D61 -> 0 | H61: 750 ml | J61: =(D61+G61)-I61 -> 0 | K61: =(('[1]PURCHASE COST'!D60/12)+(('[1]PURCHASE COST'!D60/12)*3.87%))*I61 -> 0 | M61: =D61-I61 -> 0
C62: 500 ml | D62: 483 | E62: =(('[1]PURCHASE COST'!D61/18)+(('[1]PURCHASE COST'!D61/18)*3.87%))*D62 -> 224089.14 | H62: 500 ml | I62: 483 | J62: =(D62+G62)-I62 -> 0 | K62: =(('[1]PURCHASE COST'!D61/18)+(('[1]PURCHASE COST'!D61/18)*3.87%))*I62 -> 224089.14 | M62: =D62-I62 -> 0
C63: 375 ml | E63: =(('[1]PURCHASE COST'!D62/24)+(('[1]PURCHASE COST'!D62/24)*3.87%))*D63 -> 0 | H63: 375 ml | J63: =(D63+G63)-I63 -> 0 | K63: =(('[1]PURCHASE COST'!D62/24)+(('[1]PURCHASE COST'!D62/24)*3.87%))*I63 -> 0 | M63: =D63-I63 -> 0
C64: 60 ml | D64: 1.5 | E64: =((('[1]PURCHASE COST'!D61/18)+(('[1]PURCHASE COST'!D61/18)*3.87%))/8.25)*D64 -> 84.35503 | H64: 60 ml | I64: 0 | J64: =((((D62+G62)-I62)*8.25)+D64)-I64 -> 1.5 | K64: =((('[1]PURCHASE COST'!D61/18)+(('[1]PURCHASE COST'!D61/18)*3.87%))/8.25)*I64 -> 0
A65: 13 | B65: M.C VSOP BRANDY | C65: 1000 ml | D65: 7 | E65: =(('[1]PURCHASE COST'!D64/9)+(('[1]PURCHASE COST'!D64/9)*3.87%))*D65 -> 6656.9129 | F65: =E65+E66+E67+E68+E69 -> 7579.0826 | H65: 1000 ml | I65: 7 | K65: =(('[1]PURCHASE COST'!D64/9)+(('[1]PURCHASE COST'!D64/9)*3.87%))*I65 -> 6656.9129 | L65: =K65+K66+K67+K68+K69 -> 7233.269 | M65: =D65-I65 -> 0
C66: 750 ml | E66: =(('[1]PURCHASE COST'!D65/12)+(('[1]PURCHASE COST'!D65/12)*3.87%))*D66 -> 0 | H66: 750 ml | J66: =(D66+G66)-I66 -> 0 | K66: =(('[1]PURCHASE COST'!D65/12)+(('[1]PURCHASE COST'!D65/12)*3.87%))*I66 -> 0 | M66: =D66-I66 -> 0
C67: 500 ml | E67: =(('[1]PURCHASE COST'!D66/18)+(('[1]PURCHASE COST'!D66/18)*3.87%))*D67 -> 0 | H67: 500 ml | J67: =(D67+G67)-I67 -> 0 | K67: =(('[1]PURCHASE COST'!D66/18)+(('[1]PURCHASE COST'!D66/18)*3.87%))*I67 -> 0 | M67: =D67-I67 -> 0
C68: 375 ml | E68: =(('[1]PURCHASE COST'!D67/24)+(('[1]PURCHASE COST'!D67/24)*3.87%))*D68 -> 0 | H68: 375 ml | J68: =(D68+G68)-I68 -> 0 | K68: =(('[1]PURCHASE COST'!D67/24)+(('[1]PURCHASE COST'!D67/24)*3.87%))*I68 -> 0 | M68: =D68-I68 -> 0
C69: 60 ml | D69: 16 | E69: =((('[1]PURCHASE COST'!D64/9)+(('[1]PURCHASE COST'!D64/9)*3.87%))/16.5)*D69 -> 922.16975 | H69: 60 ml | I69: 10 | J69: =((((D65+G65)-I65)*16.5)+D69)-I69 -> 6 | K69: =((('[1]PURCHASE COST'!D64/9)+(('[1]PURCHASE COST'!D64/9)*3.87%))/16.5)*I69 -> 576.35609
A70: 14 | B70: M.C WHISKEY | C70: 1000 ml | D70: 6 | E70: =(('[1]PURCHASE COST'!D69/9)+(('[1]PURCHASE COST'!D69/9)*3.87%))*D70 -> 7021.612 | F70: =E70+E71+E72+E73+E74 -> 7908.1792 | H70: 1000 ml | I70: 6 | K70: =(('[1]PURCHASE COST'!D69/9)+(('[1]PURCHASE COST'!D69/9)*3.87%))*I70 -> 7021.612 | L70: =K70+K71+K72+K73+K74 -> 7837.2538 | M70: =D70-I70 -> 0
C71: 750 ml | E71: =(('[1]PURCHASE COST'!D70/12)+(('[1]PURCHASE COST'!D70/12)*3.87%))*D71 -> 0 | H71: 750 ml | J71: =(D71+G71)-I71 -> 0 | K71: =(('[1]PURCHASE COST'!D70/12)+(('[1]PURCHASE COST'!D70/12)*3.87%))*I71 -> 0 | M71: =D71-I71 -> 0
C72: 500 ml | E72: =(('[1]PURCHASE COST'!D71/18)+(('[1]PURCHASE COST'!D71/18)*3.87%))*D72 -> 0 | H72: 500 ml | J72: =(D72+G72)-I72 -> 0 | K72: =(('[1]PURCHASE COST'!D71/18)+(('[1]PURCHASE COST'!D71/18)*3.87%))*I72 -> 0 | M72: =D72-I72 -> 0
C73: 375 ml | E73: =(('[1]PURCHASE COST'!D72/24)+(('[1]PURCHASE COST'!D72/24)*3.87%))*D73 -> 0 | H73: 375 ml | J73: =(D73+G73)-I73 -> 0 | K73: =(('[1]PURCHASE COST'!D72/24)+(('[1]PURCHASE COST'!D72/24)*3.87%))*I73 -> 0 | M73: =D73-I73 -> 0
C74: 60 ml | D74: 12.5 | E74: =((('[1]PURCHASE COST'!D69/9)+(('[1]PURCHASE COST'!D69/9)*3.87%))/16.5)*D74 -> 886.56717 | H74: 60 ml | I74: 11.5 | J74: =((((D70+G70)-I70)*16.5)+D74)-I74 -> 1 | K74: =((('[1]PURCHASE COST'!D69/9)+(('[1]PURCHASE COST'!D69/9)*3.87%))/16.5)*I74 -> 815.6418
A75: 15 | B75: GREEN LABEL WHISKEY | C75: 1000 ml | E75: =(('[1]PURCHASE COST'!D74/9)+(('[1]PURCHASE COST'!D74/9)*3.87%))*D75 -> 0 | F75: =E75+E76+E77+E78+E79 -> 24692.6 | H75: 1000 ml | K75: =(('[1]PURCHASE COST'!D74/9)+(('[1]PURCHASE COST'!D74/9)*3.87%))*I75 -> 0 | L75: =K75+K76+K77+K78+K79 -> 24194.647 | M75: =D75-I75 -> 0
C76: 750 ml | D76: 33 | E76: =(('[1]PURCHASE COST'!D75/12)+(('[1]PURCHASE COST'!D75/12)*3.87%))*D76 -> 24165.356 | H76: 750 ml | I76: 33 | J76: 0 | K76: =(('[1]PURCHASE COST'!D75/12)+(('[1]PURCHASE COST'!D75/12)*3.87%))*I76 -> 24165.356 | M76: =D76-I76 -> 0
C77: 500 ml | E77: =(('[1]PURCHASE COST'!D76/18)+(('[1]PURCHASE COST'!D76/18)*3.87%))*D77 -> 0 | H77: 500 ml | J77: =(D77+G77)-I77 -> 0 | K77: =(('[1]PURCHASE COST'!D76/18)+(('[1]PURCHASE COST'!D76/18)*3.87%))*I77 -> 0 | M77: =D77-I77 -> 0
C78: 375 ml | E78: =(('[1]PURCHASE COST'!D77/24)+(('[1]PURCHASE COST'!D77/24)*3.87%))*D78 -> 0 | H78: 375 ml | J78: =(D78+G78)-I78 -> 0 | K78: =(('[1]PURCHASE COST'!D77/24)+(('[1]PURCHASE COST'!D77/24)*3.87%))*I78 -> 0 | M78: =D78-I78 -> 0
C79: 60 ml | D79: 9 | E79: =((('[1]PURCHASE COST'!D75/12)+(('[1]PURCHASE COST'!D75/12)*3.87%))/12.5)*D79 -> 527.24412 | H79: 60 ml | I79: 0.5 | J79: =((((D76+G76)-I76)*12.5)+D79)-I79 -> 8.5 | K79: =((('[1]PURCHASE COST'!D75/12)+(('[1]PURCHASE COST'!D75/12)*3.87%))/12.5)*I79 -> 29.29134
A80: 16 | B80: LE MONTE WHITE BRANDY | C80: 1000 ml | D80: 22 | E80: =(('[1]PURCHASE COST'!D79/9)+(('[1]PURCHASE COST'!D79/9)*3.87%))*D80 -> 20667.822 | F80: =E80+E81+E82+E83+E84 -> 22414.954 | H80: 1000 ml | I80: 21 | K80: =(('[1]PURCHASE COST'!D79/9)+(('[1]PURCHASE COST'!D79/9)*3.87%))*I80 -> 19728.375 | L80: =K80+K81+K82+K83+K84 -> 21219.295 | M80: =D80-I80 -> 1
C81: 750 ml | D81: 1 | E81: =(('[1]PURCHASE COST'!D80/12)+(('[1]PURCHASE COST'!D80/12)*3.87%))*D81 -> 836.1535 | H81: 750 ml | I81: 1 | J81: =(D81+G81)-I81 -> 0 | K81: =(('[1]PURCHASE COST'!D80/12)+(('[1]PURCHASE COST'!D80/12)*3.87%))*I81 -> 836.1535 | M81: =D81-I81 -> 0
C82: 500 ml | E82: =(('[1]PURCHASE COST'!D81/18)+(('[1]PURCHASE COST'!D81/18)*3.87%))*D82 -> 0 | H82: 500 ml | J82: =(D82+G82)-I82 -> 0 | K82: =(('[1]PURCHASE COST'!D81/18)+(('[1]PURCHASE COST'!D81/18)*3.87%))*I82 -> 0 | M82: =D82-I82 -> 0
C83: 375 ml | E83: =(('[1]PURCHASE COST'!D82/24)+(('[1]PURCHASE COST'!D82/24)*3.87%))*D83 -> 0 | H83: 375 ml | J83: =(D83+G83)-I83 -> 0 | K83: =(('[1]PURCHASE COST'!D82/24)+(('[1]PURCHASE COST'!D82/24)*3.87%))*I83 -> 0 | M83: =D83-I83 -> 0
C84: 60 ml | D84: 16 | E84: =((('[1]PURCHASE COST'!D79/9)+(('[1]PURCHASE COST'!D79/9)*3.87%))/16.5)*D84 -> 910.97837 | H84: 60 ml | I84: 11.5 | J84: =((((D80+G80)-I80)*16.5)+D84)-I84 -> 21 | K84: =((('[1]PURCHASE COST'!D79/9)+(('[1]PURCHASE COST'!D79/9)*3.87%))/16.5)*I84 -> 654.7657
A85: 17 | B85: CONTESSA WHITE RUM | C85: 1000 ml | D85: 69 | E85: =(('[1]PURCHASE COST'!D84/9)+(('[1]PURCHASE COST'!D84/9)*3.87%))*D85 -> 59725.25 | F85: =E85+E86+E87+E88+E89 -> 60040.008 | H85: 1000 ml | I85: 68 | K85: =(('[1]PURCHASE COST'!D84/9)+(('[1]PURCHASE COST'!D84/9)*3.87%))*I85 -> 58859.667 | L85: =K85+K86+K87+K88+K89 -> 59305.573 | M85: =D85-I85 -> 1
C86: 750 ml | E86: =(('[1]PURCHASE COST'!D85/12)+(('[1]PURCHASE COST'!D85/12)*3.87%))*D86 -> 0 | H86: 750 ml | J86: =(D86+G86)-I86 -> 0 | K86: =(('[1]PURCHASE COST'!D85/12)+(('[1]PURCHASE COST'!D85/12)*3.87%))*I86 -> 0 | M86: =D86-I86 -> 0
C87: 500 ml | E87: =(('[1]PURCHASE COST'!D86/18)+(('[1]PURCHASE COST'!D86/18)*3.87%))*D87 -> 0 | H87: 500 ml | J87: 0 | K87: =(('[1]PURCHASE COST'!D86/18)+(('[1]PURCHASE COST'!D86/18)*3.87%))*I87 -> 0 | M87: =D87-I87 -> 0
C88: 375 ml | E88: =(('[1]PURCHASE COST'!D87/24)+(('[1]PURCHASE COST'!D87/24)*3.87%))*D88 -> 0 | H88: 375 ml | J88: =(D88+G88)-I88 -> 0 | K88: =(('[1]PURCHASE COST'!D87/24)+(('[1]PURCHASE COST'!D87/24)*3.87%))*I88 -> 0 | M88: =D88-I88 -> 0
C89: 60 ml | D89: 6 | E89: =((('[1]PURCHASE COST'!D84/9)+(('[1]PURCHASE COST'!D84/9)*3.87%))/16.5)*D89 -> 314.75758 | H89: 60 ml | I89: 8.5 | J89: =((((D85+G85)-I85)*16.5)+D89)-I89 -> 14 | K89: =((('[1]PURCHASE COST'!D84/9)+(('[1]PURCHASE COST'!D84/9)*3.87%))/16.5)*I89 -> 445.90657
A90: 18 | B90: CR. NEPOLEAN GREEN BRANDY | C90: 1000 ml | E90: =(('[1]PURCHASE COST'!D89/9)+(('[1]PURCHASE COST'!D89/9)*3.87%))*D90 -> 0 | F90: =E90+E91+E92+E93+E94 -> 0 | H90: 1000 ml | K90: =(('[1]PURCHASE COST'!D89/9)+(('[1]PURCHASE COST'!D89/9)*3.87%))*I90 -> 0 | L90: =K90+K91+K92+K93+K94 -> 0 | M90: =D90-I90 -> 0
C91: 750 ml | E91: =(('[1]PURCHASE COST'!D90/12)+(('[1]PURCHASE COST'!D90/12)*3.87%))*D91 -> 0 | H91: 750 ml | J91: =(D91+G91)-I91 -> 0 | K91: =(('[1]PURCHASE COST'!D90/12)+(('[1]PURCHASE COST'!D90/12)*3.87%))*I91 -> 0 | M91: =D91-I91 -> 0
C92: 500 ml | E92: =(('[1]PURCHASE COST'!D91/18)+(('[1]PURCHASE COST'!D91/18)*3.87%))*D92 -> 0 | H92: 500 ml | J92: =(D92+G92)-I92 -> 0 | K92: =(('[1]PURCHASE COST'!D91/18)+(('[1]PURCHASE COST'!D91/18)*3.87%))*I92 -> 0 | M92: =D92-I92 -> 0
C93: 375 ml | E93: =(('[1]PURCHASE COST'!D92/24)+(('[1]PURCHASE COST'!D92/24)*3.87%))*D93 -> 0 | H93: 375 ml | J93: =(D93+G93)-I93 -> 0 | K93: =(('[1]PURCHASE COST'!D92/24)+(('[1]PURCHASE COST'!D92/24)*3.87%))*I93 -> 0 | M93: =D93-I93 -> 0
C94: 60 ml | E94: =((('[1]PURCHASE COST'!D90/12)+(('[1]PURCHASE COST'!D90/12)*3.87%))/12.5)*D94 -> 0 | H94: 60 ml | J94: =((((D90+G90)-I90)*16.5)+D94)-I94 -> 0 | K94: =((('[1]PURCHASE COST'!D90/12)+(('[1]PURCHASE COST'!D90/12)*3.87%))/12.5)*I94 -> 0
A95: 19 | B95: VINHO DE GOA RED WINE | C95: 1000 ml | E95: =(('[1]PURCHASE COST'!D94/9)+(('[1]PURCHASE COST'!D94/9)*3.87%))*D95 -> 0 | F95: =E95+E96+E97+E98+E99 -> 4704.2723 | H95: 1000 ml | K95: =(('[1]PURCHASE COST'!D94/9)+(('[1]PURCHASE COST'!D94/9)*3.87%))*I95 -> 0 | L95: =K95+K96+K97+K98+K99 -> 4688.3456 | M95: =D95-I95 -> 0
C96: 750 ml | D96: 11 | E96: =(('[1]PURCHASE COST'!D95/12)+(('[1]PURCHASE COST'!D95/12)*3.87%))*D96 -> 2189.9258 | H96: 750 ml | I96: 11 | J96: =(D96+G96)-I96 -> 0 | K96: =(('[1]PURCHASE COST'!D95/12)+(('[1]PURCHASE COST'!D95/12)*3.87%))*I96 -> 2189.9258 | M96: =D96-I96 -> 0
C97: 500 ml | E97: =(('[1]PURCHASE COST'!D96/18)+(('[1]PURCHASE COST'!D96/18)*3.87%))*D97 -> 0 | H97: 500 ml | J97: =(D97+G97)-I97 -> 0 | K97: =(('[1]PURCHASE COST'!D96/18)+(('[1]PURCHASE COST'!D96/18)*3.87%))*I97 -> 0 | M97: =D97-I97 -> 0
C98: 375 ml | D98: 21 | E98: =(('[1]PURCHASE COST'!D97/24)+(('[1]PURCHASE COST'!D97/24)*3.87%))*D98 -> 2363.0425 | H98: 375 ml | I98: 21 | J98: =(D98+G98)-I98 -> 0 | K98: =(('[1]PURCHASE COST'!D97/24)+(('[1]PURCHASE COST'!D97/24)*3.87%))*I98 -> 2363.0425 | M98: =D98-I98 -> 0
C99: 60 ml | D99: 9.5 | E99: =((('[1]PURCHASE COST'!D95/12)+(('[1]PURCHASE COST'!D95/12)*3.87%))/12.5)*D99 -> 151.30397 | H99: 60 ml | I99: 8.5 | J99: =((((D95+G95)-I95)*16.5)+D99)-I99 -> 1 | K99: =((('[1]PURCHASE COST'!D95/12)+(('[1]PURCHASE COST'!D95/12)*3.87%))/12.5)*I99 -> 135.37723
A100: 20 | B100: M.C RUM | C100: 1000 ml | D100: 46 | E100: =(('[1]PURCHASE COST'!D99/9)+(('[1]PURCHASE COST'!D99/9)*3.87%))*D100 -> 33021.427 | F100: =E100+E101+E102+E103+E104 -> 56239.572 | H100: 1000 ml | I100: 44 | K100: =(('[1]PURCHASE COST'!D99/9)+(('[1]PURCHASE COST'!D99/9)*3.87%))*I100 -> 31585.713 | L100: =K100+K101+K102+K103+K104 -> 54673.338 | M100: =D100-I100 -> 2
C101: 750 ml | E101: =(('[1]PURCHASE COST'!D100/12)+(('[1]PURCHASE COST'!D100/12)*3.87%))*D101 -> 0 | H101: 750 ml | J101: =(D101+G101)-I101 -> 0 | K101: =(('[1]PURCHASE COST'!D100/12)+(('[1]PURCHASE COST'!D100/12)*3.87%))*I101 -> 0 | M101: =D101-I101 -> 0
C102: 500 ml | D102: 49 | E102: =(('[1]PURCHASE COST'!D101/18)+(('[1]PURCHASE COST'!D101/18)*3.87%))*D102 -> 17530.948 | H102: 500 ml | I102: 49 | J102: =(D102+G102)-I102 -> 0 | K102: =(('[1]PURCHASE COST'!D101/18)+(('[1]PURCHASE COST'!D101/18)*3.87%))*I102 -> 17530.948 | M102: =D102-I102 -> 0
C103: 375 ml | D103: 19 | E103: =(('[1]PURCHASE COST'!D102/24)+(('[1]PURCHASE COST'!D102/24)*3.87%))*D103 -> 5295.6388 | H103: 375 ml | I103: 19 | J103: =(D103+G103)-I103 -> 0 | K103: =(('[1]PURCHASE COST'!D102/24)+(('[1]PURCHASE COST'!D102/24)*3.87%))*I103 -> 5295.6388 | M103: =D103-I103 -> 0
...

Sheet PRODUCT PRICE
A1: SL.No | B1: PARTICULARS | C1: VOLUME | D1: PURCHASE COST (per case)
A2: 1 | B2: CEASAR BRANDY | C2: 1000 ml
C3: 750 ml | D3: 13420
C4: 500 ml
C5: 375 ml
C6: 60 ml
A7: 2 | B7: M.C BRANDY | C7: 1000 ml | D7: 6720
C8: 750 ml
C9: 500 ml | D9: 6600
C10: 375 ml
C11: 60 ml
A12: 3 | B12: MGM ORANGE VODKA | C12: 1000 ml | D12: 6420
C13: 750 ml | D13: 7160
C14: 500 ml | D14: 6500
C15: 375 ml | D15: 7000
C16: 60 ml
A17: 4 | B17: MANSION HOUSE BRANDY | C17: 1000 ml | D17: 8240
C18: 750 ml | D18: 10520
C19: 500 ml | D19: 8640
C20: 375 ml | D20: 10620
C21: 60 ml
A22: 5 | B22: OLD CASK RUM | C22: 1000 ml | D22: 6620
C23: 750 ml
C24: 500 ml | D24: 6500
C25: 375 ml | D25: 6900
C26: 60 ml
A27: 6 | B27: CR. NEPOLEAN BRANDY | C27: 1000 ml | D27: 7420
C28: 750 ml | D28: 7960
C29: 500 ml | D29: 7600
C30: 375 ml
C31: 60 ml
A32: 7 | B32: HONEY BEE BRANDY | C32: 1000 ml | D32: 6720
C33: 750 ml
C34: 500 ml | D34: 6600
C35: 375 ml | D35: 7100
C36: 60 ml
A37: 8 | B37: OFFICER CHOICE BRANDY | C37: 1000 ml | D37: 7520
C38: 750 ml | D38: 8260
C39: 500 ml | D39: 7500
C40: 375 ml | D40: 8500
C41: 60 ml
A42: 9 | B42: 8 P.M EXCELLENCY BRANDY | C42: 1000 ml | D42: 6020
C43: 750 ml
C44: 500 ml | D44: 6300
C45: 375 ml | D45: 7100
C46: 60 ml
A47: 10 | B47: WHITE MISCHIEF BRANDY | C47: 1000 ml | D47: 6720
C48: 750 ml | D48: 6800
C49: 500 ml | D49: 6900
C50: 375 ml | D50: 7500
C51: 60 ml
A52: 11 | B52: KYRON BRANDY | C52: 1000 ml
C53: 750 ml | D53: 13620
C54: 500 ml
C55: 375 ml | D55: 13720
C56: 60 ml
A59: 12 | B59: BUDGET RUM | C59: 1000 ml
C60: 750 ml
C61: 500 ml | D61: 6100
C62: 375 ml
C63: 60 ml
A64: 13 | B64: M.C VSOP BRANDY | C64: 1000 ml | D64: 8240
C65: 750 ml | D65: 10420
C66: 500 ml | D66: 8640
C67: 375 ml | D67: 10300
C68: 60 ml
A69: 14 | B69: M.C WHISKEY | C69: 1000 ml | D69: 10140
C70: 750 ml | D70: 11120
C71: 500 ml
C72: 375 ml
C73: 60 ml
A74: 15 | B74: GREEN LABEL WHISKEY | C74: 1000 ml
C75: 750 ml | D75: 8460
C76: 500 ml | D76: 7600
C77: 375 ml | D77: 8500
C78: 60 ml
A79: 16 | B79: LE MOUNT WHITE BRANDY | C79: 1000 ml | D79: 8140
C80: 750 ml | D80: 9660
C81: 500 ml | D81: 8740
C82: 375 ml | D82: 9700
C83: 60 ml
A84: 17 | B84: CONTESSA WHITE RUM | C84: 1000 ml | D84: 7500
C85: 750 ml
C86: 500 ml | D86: 6800
C87: 375 ml
C88: 60 ml
A89: 18 | B89: CR. NEPOLEAN GREEN BRANDY | C89: 1000 ml
C90: 750 ml | D90: 14820
C91: 500 ml
C92: 375 ml
C93: 60 ml
A94: 19 | B94: VINHO DE GOA RED WINE | C94: 1000 ml
C95: 750 ml | D95: 2300
C96: 500 ml
C97: 375 ml | D97: 2600
C98: 60 ml
A99: 20 | B99: M.C RUM | C99: 1000 ml | D99: 6220
C100: 750 ml | D100: 6660
C101: 500 ml | D101: 6200
C102: 375 ml | D102: 6440
...
